bulkfileoperationsmanager/__init__.py
bulkfileoperationsmanager/bulk_operations_manager.py
bulkfileoperationsmanager/tasks/__init__.py
tests/__init__.py
tests/test_bulk_operations_manager.py
BulkFileOperationsManager-0.0.7.dist-info/LICENSE
BulkFileOperationsManager-0.0.7.dist-info/METADATA
BulkFileOperationsManager-0.0.7.dist-info/WHEEL
BulkFileOperationsManager-0.0.7.dist-info/top_level.txt
BulkFileOperationsManager-0.0.7.dist-info/RECORD
