Metadata-Version: 2.1
Name: BulkFileOperationsManager
Version: 0.0.7
Summary: Python package for managing bulk file CRUD operations.
Home-page: https://github.com/chigwell/BulkFileOperationsManager
Author: Eugene Evstafev
Author-email: chigwel@gmail.com
License: UNKNOWN
Platform: UNKNOWN
Requires-Dist: filechunkcrud ==0.0.5
